dicom_sso/__init__.py
dicom_sso/create_dicom_sso.py
dicom_sso/load_seg_mesh.py
dicom_sso/segment.py
dicom_sso/sso_vtk.py
dicom_sso/surface.py
dicom_sso/surface_segmentation.py
dicom_sso-0.2.1.dist-info/METADATA
dicom_sso-0.2.1.dist-info/WHEEL
dicom_sso-0.2.1.dist-info/entry_points.txt
dicom_sso-0.2.1.dist-info/RECORD
